mooo/__init__.py
mooo/__main__.py
mooo/proxy.py
mooo-0.1.1.dist-info/LICENSE
mooo-0.1.1.dist-info/METADATA
mooo-0.1.1.dist-info/WHEEL
mooo-0.1.1.dist-info/entry_points.txt
mooo-0.1.1.dist-info/top_level.txt
mooo-0.1.1.dist-info/RECORD
