Metadata-Version: 2.2
Name: mooo
Version: 0.1.1
Summary: A simple http proxy
Author-email: Hang <bebound@gmail.com>
License: MIT License
Project-URL: Homepage, https://github.com/bebound/mooo
Project-URL: Source, https://github.com/bebound/mooo/
Keywords: HTTP,proxy
Classifier: Development Status :: 3 - Alpha
Classifier: License :: OSI Approved :: MIT License
Classifier: Programming Language :: Python :: 3
Classifier: Programming Language :: Python :: 3.9
Classifier: Programming Language :: Python :: 3.10
Classifier: Programming Language :: Python :: 3.11
Classifier: Programming Language :: Python :: 3.12
Classifier: Programming Language :: Python :: 3.13
Classifier: Programming Language :: Python :: 3 :: Only
Requires-Python: >=3.8
License-File: LICENSE
Requires-Dist: aiohttp>=3.9.5
Provides-Extra: test
Requires-Dist: requests; extra == "test"
Requires-Dist: pytest; extra == "test"
